{
  "Header": {
    "title": "",
    "paragraph": "One of Kenya's Finest and upcoming E-Farmingn sites for buying and selling agricultural products for Farmers."
  },
  "About": {
    "paragraph": "Agrisoko revolutionizes farming with buyers using advanced technology, connecting farmers to markets efficiently, fostering sustainable agricultural practices.",
    "Why": [
      "Connecting Farmers with Buyers: We provide a digital marketplace where local farmers can showcase their produce directly to buyers and consumers. This eliminates the need for intermediaries, ensuring fair prices for farmers and fresh, quality products for buyers. ",
      "Transparent Transactions: We prioritize transparency in every transaction. Buyers can learn about the farmers behind the products they purchase, including their farming practices and values. This fosters trust and strengthens the bond between farmers and consumers.",
      "Community Engagement: We foster a sense of community among farmers, buyers, and consumers. Through educational initiatives, events, and forums, we encourage collaboration and knowledge-sharing, strengthening the local food ecosystem."
    ],
    "Why2": [
     
    ]
  },

  "Gallery": [
    {
      "image_link": "https://encrypted-tbn0.gstatic.com/images?q=tbn:ANd9GcS6YDGeDo6AYPxoLbKO-xpqXFDubMgBIICS0A&usqp=CAU",
      "name": "",
      "text": ""
    },
    {
      "image_link": "https://encrypted-tbn0.gstatic.com/images?q=tbn:ANd9GcRxncgi6vWttkjQHDmUBCr2oxzQHQmzGoWi8g&usqp=CAU",
      "name": "",
      "text": ""
    },
    {
      "image_link": "https://encrypted-tbn0.gstatic.com/images?q=tbn:ANd9GcRPP547r4t6l8hKEPL1Zi7Cf1KG2Ycr_FxWHw&usqp=CAU",
      "name": "",
      "text": ""
    },
    {
      "image_link": "https://encrypted-tbn0.gstatic.com/images?q=tbn:ANd9GcQvdnC4PQ-Etjd3rB3XgMSC0xdUK9pWubzIdQ&usqp=CAU",
      "name": "",
      "text": ""
    }
],
"Testimonials":[
  {
    "name": "COWS",
    "image_link": "https://static.wixstatic.com/media/a84228_34797c27932b418490d44c23094c2132~mv2.jpeg/v1/fill/w_489,h_366,al_c,q_80,usm_1.20_1.00_0.01,enc_auto/Brown%20Ayrshire%20cows%20grazing%20in%20a%20green%20field%20on%20Gloucester%20Vale%20Farm%20in%20Kenya.jpeg"
  },
  {
    "name": "FARM MACHINERY",
    "image_link": "https://modernfarmer.com/wp-content/uploads/2022/05/shutterstock_517244548.jpg"
  },
  {
    "name": "GREEN HOUSE",
    "image_link": "https://prod.cdn-medias.theafricareport.com/cdn-cgi/image/q=auto,f=auto,metadata=none,width=732,height=419,fit=cover/https://prod.cdn-medias.theafricareport.com/medias/2024/01/26/secondsky-e1706518729298.jpg"
  }
],

  "Services": [
    {
      "image_link": "https://encrypted-tbn0.gstatic.com/images?q=tbn:ANd9GcRQCVTYk5c4imnAbNwo09unM8ePPtfmHtsk8w&usqp=CAU",
      "name": "FRUITS",
      "text": ""
    },
    {
      "image_link": "https://encrypted-tbn0.gstatic.com/images?q=tbn:ANd9GcRycK6zjL0wHHbASEwcGeazpXysjUs27Th1-w&usqp=CAU",
      "name": "LIVESTOCKS",
      "text": ""
    },
    {
      "image_link": "https://encrypted-tbn0.gstatic.com/images?q=tbn:ANd9GcTHV_Y3aMTapyi_R43Gk8YyuiCc4xaG5-HS3g&usqp=CAU",
      "name": "VEGETABLES",
      "text": ""
    },
    {
      "image_link": "https://encrypted-tbn0.gstatic.com/images?q=tbn:ANd9GcS3wnAAGnIDSd2tmJEnsEFgIyWFvHwP8ynb4Q&usqp=CAU",
      "name": "MEAT AND POULTRY",
      "text": ""
    },
    {
      "image_link": "https://encrypted-tbn0.gstatic.com/images?q=tbn:ANd9GcR_zSAUCTytcmDXF-MmnWrPO9iT0i6N9ufVDQ&usqp=CAU",
      "name": "FLOWERS",
      "text": ""
    },
    {
      "image_link": "https://encrypted-tbn0.gstatic.com/images?q=tbn:ANd9GcQSeRc0nY_Hks6zot6sgBnYx_ayA-6inagDSg&usqp=CAU",
      "name": "HERBS",
      "text": ""
    }
],

  "Team": [
    {
      "img": "img/team/black-guy4.jpg",
      "name": "John ",
      "job": "Director"
    },
    {
      "img": "img/team/black-guy3.jpg",
      "name": "Conrad",
      "job": "Senior Designer"
    },
    {
      "img": "img/team/black-guy2.jpg",
      "name": "Willy",
      "job": "Senior Designer"
    },
    {
      "img": "img/team/black-guy5.jpg",
      "name": "Jim",
      "job": "Project Manager"
    },
    {
      "img": "img/team/girl1.jpg",
      "name": "Faith ",
      "job": "Director"
    },
    {
      "img": "img/team/blackGuy6.jpg",
      "name": "Owen",
      "job": "Senior Designer"
    },
    {
      "img": "img/team/blackguy1.jpg",
      "name": "Amaar",
      "job": "Senior Designer"
    },
    {
      "img": "img/team/blackman7.jpg",
      "name": "Khalid",
      "job": "Project Manager"
    }

  ],
  "Contact": {
    "address": "Vedic Hse, 3rd Flr Moi Ave, 4994-00506 Nyayo Stadium.Nairobi",
    "phone": "+254720000000",
    "email": "agri-soko@company.com",
    "facebook": "fb.com",
    "twitter": "twitter.com",
    "youtube": "youtube.com"
  },
  "Features": [
    {
      "icon": "fa fa-comments-o",
      "title": "Lorem ipsum",
      "text": "Lorem ipsum dolor sit amet placerat facilisis felis mi in tempus eleifend pellentesque natoque etiam."
    },
    {
      "icon": "fa fa-bullhorn",
      "title": "Lorem ipsum",
      "text": "Lorem ipsum dolor sit amet placerat facilisis felis mi in tempus eleifend pellentesque natoque etiam."
    },
    {
      "icon": "fa fa-group",
      "title": "Lorem ipsum",
      "text": "Lorem ipsum dolor sit amet placerat facilisis felis mi in tempus eleifend pellentesque natoque etiam."
    },
    {
      "icon": "fa fa-magic",
      "title": "Lorem ipsum",
      "text": "Lorem ipsum dolor sit amet placerat facilisis felis mi in tempus eleifend pellentesque natoque etiam."
    }
  ]
}

